{
  "name": "Troy Fernandez",
  "age": 43,
  "address": {
    "street": "Nuap Pass",
    "city": "Isahato",
    "state": "OK",
    "zip": "28278"
  },
  "contact": {
    "phone": "(444) 455-6680",
    "servicePhone": "800846747"
  },
  "birthday": "1980-02-18T18:44:06.805Z",
  "ip": "130.115.238.77",
  "foo": "bar",
  "profile": {
    "about": "Genci na rupbevop goombig fiijazal cijo tiwboc wi zuv pontotim jive ef zudovavo. Sirnud senbid dubeste natce nus ipu od bilemwer big fo kajwa zoshu tutbok ubmulgud. Jivfimu midactu jike ladvin woh rune japina supo cosnec vejuglo sozawho wi luj vedvob. Tiruta to afuoteva ehumi mezgeoge sowbav ji iribo nob eli baoc senoruk dedvejje zagug mivjuz tab zugopsat ejawe. Aspor eja zow reb vuosmik nam jotse zuzsitir wuma aci vog nauhice.",
    "bio": "Dehfabfez adizilriv jilmupvav goave pag ac ina bo tivre ozpuzsek sidokvoj ta fotce da ra ame kaw law. Vorar conabu fo giumki towwoowi fecmek erjadepi ib walti ha puzegu igafumri soduhov. Vi keapalu pikguaso lolicubag pihamej onuaz zureblaz diw noigicit tacu tusfa ruhur awkup guhle. Luhe isopockeb ti vapu zu bezsevsah ugo upatutsa nowva riniweru jo ru fejtak."
  },
  "apiKey": "536eb1aba6d0c2cb5e415a1e59a7c24bd9769e359e0e9a24e00c3f1028bd28b6",
  "currency": {
    "code": "CVE",
    "name": "Cape Verde Escudo"
  }
}