{
  "name": "Effie Burns",
  "age": 23,
  "address": {
    "street": "Zemne Turnpike",
    "city": "Vuhmulus",
    "state": "CO",
    "zip": "26170"
  },
  "contact": {
    "phone": "(371) 817-3841",
    "servicePhone": "800898929"
  },
  "birthday": "1971-03-29T02:36:57.314Z",
  "ip": "76.8.22.30",
  "foo": "bar",
  "profile": {
    "about": "Ziw wadu wukohvin bikni laj fu awuwi pi ogeji juhekfe zoiga oja abedciv ujpedo uliru irfaz deltes. Ro fakja ihakba uzori duldekro vum go jokvesi comkoh inkapo ajoebi jo fu tespuho. Vijhidoh ew gevgabrec huslignez satodmup zar jeszeoz wulbesvuj fad lipot musbeb osehu osujapte je ba kijlub. Ke adpafvug hiete mowun dubesi feha udiru beiz vu oc wadu pufebicaj se eslocaf oflul gu ifsi.",
    "bio": "Rerlimu wujole uzvigguc zef appa rurmah lijceul vahbi vim os oriennu ni ga wiremihip vul. Afzalob galseko fu ogi finfipe hutjodig to rap pov utki vo bona vasfadtop pub. En zuvet daw zifomefol lahedma oda bu kak hokjafajo en goh rohup nofuw gec. Roju dudzem pivsopupo nalhecka acahu fecnahki zafca ulecazuw hutdap epu edo hitsabvu. Ku cac polema le tus bojili has huwog afobka cispawfe nobto gekhalin nilu. Jahav jiferus sepetil winwo harehucu fijcav je jusoodi zebnege abivo vouha wiziw. Fobduhaw le giw to veh lag afva ek aki fuza ip jar."
  },
  "apiKey": "ace6982ecd1835b4a2e548664dab6ffd2c46442b75374039c8be82065f53873c",
  "currency": {
    "code": "TTD",
    "name": "Trinidad and Tobago Dollar"
  }
}